[
  {
    "id": 347603,
    "mandante": "Macapá",
    "visitante": "Ypiranga-AP",
    "logoMandante": "https://s.sde.globo.com/media/organizations/2014/01/23/macapa-30.png",
    "logoVisitante": "https://s.sde.globo.com/media/organizations/2022/06/07/ypiranga--30.png",
    "golsMandante": 0,
    "golsVisitante": 0,
    "placar": "0 x 0",
    "placarHT": null,
    "tempo": "",
    "tempoExtra": null,
    "status": "Ao vivo",
    "statusRaw": "LIVE",
    "liga": "Campeonato Amapaense",
    "ligaId": null,
    "ligaOriginal": "Campeonato Amapaense",
    "ligaLogo": null,
    "estadio": "Augusto Antunes",
    "cidade": null,
    "horario": "09:00",
    "timestamp": 1772366400000,
    "fonte": "globo",
    "transmissao": []
  },
  {
    "id": 339237,
    "mandante": "Elche",
    "visitante": "Espanyol",
    "logoMandante": "https://s.sde.globo.com/media/organizations/2013/09/25/Elche_CF_logo-30.png",
    "logoVisitante": "https://s.sde.globo.com/media/organizations/2024/11/02/30_espanyol.png",
    "golsMandante": 0,
    "golsVisitante": 0,
    "placar": "0 x 0",
    "placarHT": null,
    "tempo": "",
    "tempoExtra": null,
    "status": "Ao vivo",
    "statusRaw": "LIVE",
    "liga": "La Liga",
    "ligaId": null,
    "ligaOriginal": "La Liga",
    "ligaLogo": null,
    "estadio": "Manuel Martínez Valero",
    "cidade": null,
    "horario": "10:00",
    "timestamp": 1772370000000,
    "fonte": "globo",
    "transmissao": [
      "Disney+",
      "Cartola"
    ]
  },
  {
    "id": 345983,
    "mandante": "Juventus-SP",
    "visitante": "XV de Piracicaba",
    "logoMandante": "https://s.sde.globo.com/media/organizations/2025/02/20/Juventus-30x30_iQ2wkRM.png",
    "logoVisitante": "https://s.sde.globo.com/media/organizations/2014/12/03/Escudo-XV-Piracicaba30.png",
    "golsMandante": 0,
    "golsVisitante": 0,
    "placar": "0 x 0",
    "placarHT": null,
    "tempo": "",
    "tempoExtra": null,
    "status": "Ao vivo",
    "statusRaw": "LIVE",
    "liga": "Campeonato Paulista Série A2",
    "ligaId": null,
    "ligaOriginal": "Campeonato Paulista Série A2",
    "ligaLogo": null,
    "estadio": "Rua Javari",
    "cidade": null,
    "horario": "10:00",
    "timestamp": 1772370000000,
    "fonte": "globo",
    "transmissao": []
  },
  {
    "id": 345988,
    "mandante": "Osasco Sporting",
    "visitante": "Ituano",
    "logoMandante": "https://s.sde.globo.com/media/organizations/2026/01/03/Osasco_Sporting-30-x-30.png",
    "logoVisitante": "https://s.sde.globo.com/media/organizations/2017/03/09/ituano_30.png",
    "golsMandante": 0,
    "golsVisitante": 0,
    "placar": "0 x 0",
    "placarHT": null,
    "tempo": "",
    "tempoExtra": null,
    "status": "Ao vivo",
    "statusRaw": "LIVE",
    "liga": "Campeonato Paulista Série A2",
    "ligaId": null,
    "ligaOriginal": "Campeonato Paulista Série A2",
    "ligaLogo": null,
    "estadio": "Prefeito José Liberatti",
    "cidade": null,
    "horario": "10:00",
    "timestamp": 1772370000000,
    "fonte": "globo",
    "transmissao": []
  },
  {
    "id": 345984,
    "mandante": "Linense",
    "visitante": "Santo André",
    "logoMandante": "https://s.sde.globo.com/media/teams/2016/02/13/Linense-logo30.png",
    "logoVisitante": "https://s.sde.globo.com/media/organizations/2017/02/02/SantoAndre-30.png",
    "golsMandante": 0,
    "golsVisitante": 0,
    "placar": "0 x 0",
    "placarHT": null,
    "tempo": "",
    "tempoExtra": null,
    "status": "Ao vivo",
    "statusRaw": "LIVE",
    "liga": "Campeonato Paulista Série A2",
    "ligaId": null,
    "ligaOriginal": "Campeonato Paulista Série A2",
    "ligaLogo": null,
    "estadio": "Gilbertão (SP)",
    "cidade": null,
    "horario": "10:00",
    "timestamp": 1772370000000,
    "fonte": "globo",
    "transmissao": []
  },
  {
    "id": 345982,
    "mandante": "Monte Azul",
    "visitante": "Água Santa",
    "logoMandante": "https://s.sde.globo.com/media/organizations/2026/01/14/30-_0001_Monte-Azul-SP.png",
    "logoVisitante": "https://s.sde.globo.com/media/organizations/2022/01/19/30_Agua-Santa.png",
    "golsMandante": 0,
    "golsVisitante": 0,
    "placar": "0 x 0",
    "placarHT": null,
    "tempo": "",
    "tempoExtra": null,
    "status": "Ao vivo",
    "statusRaw": "LIVE",
    "liga": "Campeonato Paulista Série A2",
    "ligaId": null,
    "ligaOriginal": "Campeonato Paulista Série A2",
    "ligaLogo": null,
    "estadio": "Otacília Patrício Arroyo",
    "cidade": null,
    "horario": "10:00",
    "timestamp": 1772370000000,
    "fonte": "globo",
    "transmissao": []
  },
  {
    "id": 346693,
    "mandante": "Itapirense",
    "visitante": "União São João",
    "logoMandante": "https://s.sde.globo.com/media/organizations/2021/12/15/itapirense-30.png",
    "logoVisitante": "https://s.sde.globo.com/media/organizations/2012/03/15/30_uniao_sao_joao.png",
    "golsMandante": 0,
    "golsVisitante": 0,
    "placar": "0 x 0",
    "placarHT": null,
    "tempo": "",
    "tempoExtra": null,
    "status": "Ao vivo",
    "statusRaw": "LIVE",
    "liga": "Campeonato Paulista Série A3",
    "ligaId": null,
    "ligaOriginal": "Campeonato Paulista Série A3",
    "ligaLogo": null,
    "estadio": "Coronel Chico Vieira",
    "cidade": null,
    "horario": "10:00",
    "timestamp": 1772370000000,
    "fonte": "globo",
    "transmissao": []
  },
  {
    "id": 346692,
    "mandante": "Rio Claro",
    "visitante": "EC São Bernardo",
    "logoMandante": "https://s.sde.globo.com/media/organizations/2016/03/20/rio-claro-fc30.png",
    "logoVisitante": "https://s.sde.globo.com/media/organizations/2021/12/14/escudo-ecbernardo30.png",
    "golsMandante": 0,
    "golsVisitante": 0,
    "placar": "0 x 0",
    "placarHT": null,
    "tempo": "",
    "tempoExtra": null,
    "status": "Ao vivo",
    "statusRaw": "LIVE",
    "liga": "Campeonato Paulista Série A3",
    "ligaId": null,
    "ligaOriginal": "Campeonato Paulista Série A3",
    "ligaLogo": null,
    "estadio": "Augusto Schmidt",
    "cidade": null,
    "horario": "10:00",
    "timestamp": 1772370000000,
    "fonte": "globo",
    "transmissao": []
  },
  {
    "id": 346687,
    "mandante": "Portuguesa Santista",
    "visitante": "Catanduva",
    "logoMandante": "https://s.sde.globo.com/media/organizations/2023/09/22/port_peqq.png",
    "logoVisitante": "https://s.sde.globo.com/media/organizations/2018/02/12/CatanduvaFC__30px.png",
    "golsMandante": 0,
    "golsVisitante": 0,
    "placar": "0 x 0",
    "placarHT": null,
    "tempo": "",
    "tempoExtra": null,
    "status": "Ao vivo",
    "statusRaw": "LIVE",
    "liga": "Campeonato Paulista Série A3",
    "ligaId": null,
    "ligaOriginal": "Campeonato Paulista Série A3",
    "ligaLogo": null,
    "estadio": "Ulrico Mursa",
    "cidade": null,
    "horario": "10:00",
    "timestamp": 1772370000000,
    "fonte": "globo",
    "transmissao": []
  },
  {
    "id": 339715,
    "mandante": "Brighton",
    "visitante": "Nottingham Forest",
    "logoMandante": "https://s.sde.globo.com/media/organizations/2024/04/25/Brighton_-30.png",
    "logoVisitante": "https://s.sde.globo.com/media/organizations/2017/09/15/Nottingham_Forest-30x30.png",
    "golsMandante": 0,
    "golsVisitante": 0,
    "placar": "0 x 0",
    "placarHT": null,
    "tempo": "",
    "tempoExtra": null,
    "status": "Ao vivo",
    "statusRaw": "LIVE",
    "liga": "Premier League",
    "ligaId": null,
    "ligaOriginal": "Premier League",
    "ligaLogo": null,
    "estadio": "Falmer Stadium",
    "cidade": null,
    "horario": "11:00",
    "timestamp": 1772373600000,
    "fonte": "globo",
    "transmissao": [
      "Disney+",
      "Cartola"
    ]
  },
  {
    "id": 339717,
    "mandante": "Fulham",
    "visitante": "Tottenham",
    "logoMandante": "https://s.sde.globo.com/media/organizations/2024/10/04/fulham-30-72606.png",
    "logoVisitante": "https://s.sde.globo.com/media/organizations/2017/10/16/Totheham-30.png",
    "golsMandante": 0,
    "golsVisitante": 0,
    "placar": "0 x 0",
    "placarHT": null,
    "tempo": "",
    "tempoExtra": null,
    "status": "Ao vivo",
    "statusRaw": "LIVE",
    "liga": "Premier League",
    "ligaId": null,
    "ligaOriginal": "Premier League",
    "ligaLogo": null,
    "estadio": "Craven Cottage",
    "cidade": null,
    "horario": "11:00",
    "timestamp": 1772373600000,
    "fonte": "globo",
    "transmissao": [
      "Disney+",
      "Cartola"
    ]
  },
  {
    "id": 339720,
    "mandante": "Manchester United",
    "visitante": "Crystal Palace",
    "logoMandante": "https://s.sde.globo.com/media/teams/2014/04/14/manchester_united_30x30.png",
    "logoVisitante": "https://s.sde.globo.com/media/organizations/2018/03/03/Crystal_Palace30.png",
    "golsMandante": 0,
    "golsVisitante": 0,
    "placar": "0 x 0",
    "placarHT": null,
    "tempo": "",
    "tempoExtra": null,
    "status": "Ao vivo",
    "statusRaw": "LIVE",
    "liga": "Premier League",
    "ligaId": null,
    "ligaOriginal": "Premier League",
    "ligaLogo": null,
    "estadio": "Old Trafford",
    "cidade": null,
    "horario": "11:00",
    "timestamp": 1772373600000,
    "fonte": "globo",
    "transmissao": [
      "Disney+",
      "Cartola"
    ]
  },
  {
    "id": 340096,
    "mandante": "Sassuolo",
    "visitante": "Atalanta",
    "logoMandante": "https://s.sde.globo.com/media/organizations/2013/10/07/sassuolo-30.png",
    "logoVisitante": "https://s.sde.globo.com/media/organizations/2024/05/22/30-_0001_Atalanta.png",
    "golsMandante": 0,
    "golsVisitante": 0,
    "placar": "0 x 0",
    "placarHT": null,
    "tempo": "",
    "tempoExtra": null,
    "status": "Ao vivo",
    "statusRaw": "LIVE",
    "liga": "Campeonato Italiano",
    "ligaId": null,
    "ligaOriginal": "Campeonato Italiano",
    "ligaLogo": null,
    "estadio": "Città del Tricolore",
    "cidade": null,
    "horario": "11:00",
    "timestamp": 1772373600000,
    "fonte": "globo",
    "transmissao": [
      "Disney+"
    ]
  },
  {
    "id": 340429,
    "mandante": "Paris FC",
    "visitante": "Nice",
    "logoMandante": "https://s.sde.globo.com/media/organizations/2023/01/30/paris-fc-58459.png",
    "logoVisitante": "https://s.sde.globo.com/media/organizations/2025/09/02/nice-30.png",
    "golsMandante": 0,
    "golsVisitante": 0,
    "placar": "0 x 0",
    "placarHT": null,
    "tempo": "",
    "tempoExtra": null,
    "status": "Ao vivo",
    "statusRaw": "LIVE",
    "liga": "Campeonato Francês",
    "ligaId": null,
    "ligaOriginal": "Campeonato Francês",
    "ligaLogo": null,
    "estadio": "Sébastien Charléty",
    "cidade": null,
    "horario": "11:00",
    "timestamp": 1772373600000,
    "fonte": "globo",
    "transmissao": [
      "Prime Vídeo"
    ]
  },
  {
    "id": 340780,
    "mandante": "Stuttgart",
    "visitante": "Wolfsburg",
    "logoMandante": "https://s.sde.globo.com/media/organizations/2025/09/02/stuttgard-30.png",
    "logoVisitante": "https://s.sde.globo.com/media/teams/2015/03/19/Wolfsburg30.png",
    "golsMandante": 0,
    "golsVisitante": 0,
    "placar": "0 x 0",
    "placarHT": null,
    "tempo": "",
    "tempoExtra": null,
    "status": "Agendado",
    "statusRaw": "NS",
    "liga": "Bundesliga",
    "ligaId": null,
    "ligaOriginal": "Bundesliga",
    "ligaLogo": null,
    "estadio": "Arena Stuttgart",
    "cidade": null,
    "horario": "11:30",
    "timestamp": 1772375400000,
    "fonte": "globo",
    "transmissao": [
      "sportv",
      "globoplay"
    ]
  },
  {
    "id": 339244,
    "mandante": "Valencia",
    "visitante": "Osasuna",
    "logoMandante": "https://s.sde.globo.com/media/teams/2013/09/16/valencia_30x30.png",
    "logoVisitante": "https://s.sde.globo.com/media/organizations/2011/03/31/osasuna-30.png",
    "golsMandante": 0,
    "golsVisitante": 0,
    "placar": "0 x 0",
    "placarHT": null,
    "tempo": "",
    "tempoExtra": null,
    "status": "Agendado",
    "statusRaw": "NS",
    "liga": "La Liga",
    "ligaId": null,
    "ligaOriginal": "La Liga",
    "ligaLogo": null,
    "estadio": "Mestalla",
    "cidade": null,
    "horario": "12:15",
    "timestamp": 1772378100000,
    "fonte": "globo",
    "transmissao": [
      "Disney+",
      "Cartola"
    ]
  },
  {
    "id": 340426,
    "mandante": "Lille",
    "visitante": "Nantes",
    "logoMandante": "https://s.sde.globo.com/media/organizations/2018/10/28/losc-lille-30.png",
    "logoVisitante": "https://s.sde.globo.com/media/organizations/2024/07/26/logo-nantes-30.png",
    "golsMandante": 0,
    "golsVisitante": 0,
    "placar": "0 x 0",
    "placarHT": null,
    "tempo": "",
    "tempoExtra": null,
    "status": "Agendado",
    "statusRaw": "NS",
    "liga": "Campeonato Francês",
    "ligaId": null,
    "ligaOriginal": "Campeonato Francês",
    "ligaLogo": null,
    "estadio": "Pierre-Mauroy",
    "cidade": null,
    "horario": "13:15",
    "timestamp": 1772381700000,
    "fonte": "globo",
    "transmissao": [
      "Prime Vídeo"
    ]
  },
  {
    "id": 340425,
    "mandante": "Metz",
    "visitante": "Brest",
    "logoMandante": "https://s.sde.globo.com/media/organizations/2023/11/21/metz-30x30-65318.png",
    "logoVisitante": "https://s.sde.globo.com/media/organizations/2024/11/25/30_Brest.png",
    "golsMandante": 0,
    "golsVisitante": 0,
    "placar": "0 x 0",
    "placarHT": null,
    "tempo": "",
    "tempoExtra": null,
    "status": "Agendado",
    "statusRaw": "NS",
    "liga": "Campeonato Francês",
    "ligaId": null,
    "ligaOriginal": "Campeonato Francês",
    "ligaLogo": null,
    "estadio": "Saint-Symphorien",
    "cidade": null,
    "horario": "13:15",
    "timestamp": 1772381700000,
    "fonte": "globo",
    "transmissao": []
  },
  {
    "id": 340424,
    "mandante": "Lorient",
    "visitante": "Auxerre",
    "logoMandante": "https://s.sde.globo.com/media/teams/2015/07/17/Lorient30.png",
    "logoVisitante": "https://s.sde.globo.com/media/organizations/2012/04/27/auxerre30.png",
    "golsMandante": 0,
    "golsVisitante": 0,
    "placar": "0 x 0",
    "placarHT": null,
    "tempo": "",
    "tempoExtra": null,
    "status": "Agendado",
    "statusRaw": "NS",
    "liga": "Campeonato Francês",
    "ligaId": null,
    "ligaOriginal": "Campeonato Francês",
    "ligaLogo": null,
    "estadio": "Stade Yves Allainmat",
    "cidade": null,
    "horario": "13:15",
    "timestamp": 1772381700000,
    "fonte": "globo",
    "transmissao": []
  },
  {
    "id": 339713,
    "mandante": "Arsenal",
    "visitante": "Chelsea",
    "logoMandante": "https://s.sde.globo.com/media/teams/2013/09/16/arsenal_30x30.png",
    "logoVisitante": "https://s.sde.globo.com/media/teams/2013/09/16/chelsea_30x30.png",
    "golsMandante": 0,
    "golsVisitante": 0,
    "placar": "0 x 0",
    "placarHT": null,
    "tempo": "",
    "tempoExtra": null,
    "status": "Agendado",
    "statusRaw": "NS",
    "liga": "Premier League",
    "ligaId": null,
    "ligaOriginal": "Premier League",
    "ligaLogo": null,
    "estadio": "Arsenal Stadium",
    "cidade": null,
    "horario": "13:30",
    "timestamp": 1772382600000,
    "fonte": "globo",
    "transmissao": [
      "Disney+",
      "Cartola"
    ]
  },
  {
    "id": 340777,
    "mandante": "Eintracht Frankfurt",
    "visitante": "Freiburg",
    "logoMandante": "https://s.sde.globo.com/media/organizations/2012/04/27/Eintrachtfrankfurt30.png",
    "logoVisitante": "https://s.sde.globo.com/media/organizations/2012/04/27/Freiburg30.png",
    "golsMandante": 0,
    "golsVisitante": 0,
    "placar": "0 x 0",
    "placarHT": null,
    "tempo": "",
    "tempoExtra": null,
    "status": "Agendado",
    "statusRaw": "NS",
    "liga": "Bundesliga",
    "ligaId": null,
    "ligaOriginal": "Bundesliga",
    "ligaLogo": null,
    "estadio": "Frankfurt Stadion",
    "cidade": null,
    "horario": "13:30",
    "timestamp": 1772382600000,
    "fonte": "globo",
    "transmissao": []
  },
  {
    "id": 340095,
    "mandante": "Torino",
    "visitante": "Lazio",
    "logoMandante": "https://s.sde.globo.com/media/teams/2015/03/19/Toniro-FC-30.png",
    "logoVisitante": "https://s.sde.globo.com/media/organizations/2011/01/26/lazio_30x30.png",
    "golsMandante": 0,
    "golsVisitante": 0,
    "placar": "0 x 0",
    "placarHT": null,
    "tempo": "",
    "tempoExtra": null,
    "status": "Agendado",
    "statusRaw": "NS",
    "liga": "Campeonato Italiano",
    "ligaId": null,
    "ligaOriginal": "Campeonato Italiano",
    "ligaLogo": null,
    "estadio": "Olímpico Grande Torino",
    "cidade": null,
    "horario": "14:00",
    "timestamp": 1772384400000,
    "fonte": "globo",
    "transmissao": [
      "Disney+"
    ]
  },
  {
    "id": 339236,
    "mandante": "Betis",
    "visitante": "Sevilla",
    "logoMandante": "https://s.sde.globo.com/media/organizations/2018/01/18/Real-Betis-30.png",
    "logoVisitante": "https://s.sde.globo.com/media/organizations/2011/03/31/Sevillafc-escudo-futbol30.png",
    "golsMandante": 0,
    "golsVisitante": 0,
    "placar": "0 x 0",
    "placarHT": null,
    "tempo": "",
    "tempoExtra": null,
    "status": "Agendado",
    "statusRaw": "NS",
    "liga": "La Liga",
    "ligaId": null,
    "ligaOriginal": "La Liga",
    "ligaLogo": null,
    "estadio": "Benito Villamarín",
    "cidade": null,
    "horario": "14:30",
    "timestamp": 1772386200000,
    "fonte": "globo",
    "transmissao": [
      "Disney+",
      "Cartola"
    ]
  },
  {
    "id": 349869,
    "mandante": "Santos",
    "visitante": "Cruzeiro",
    "logoMandante": "https://s.sde.globo.com/media/organizations/2014/04/14/santos_30x30.png",
    "logoVisitante": "https://s.sde.globo.com/media/organizations/2021/02/13/30_cruzeiro-2021.png",
    "golsMandante": 0,
    "golsVisitante": 0,
    "placar": "0 x 0",
    "placarHT": null,
    "tempo": "",
    "tempoExtra": null,
    "status": "Agendado",
    "statusRaw": "NS",
    "liga": "Campeonato Brasileiro sub-20",
    "ligaId": null,
    "ligaOriginal": "Campeonato Brasileiro sub-20",
    "ligaLogo": null,
    "estadio": "CT Rei Pelé",
    "cidade": null,
    "horario": "15:00",
    "timestamp": 1772388000000,
    "fonte": "globo",
    "transmissao": []
  },
  {
    "id": 349870,
    "mandante": "Vasco",
    "visitante": "São Paulo",
    "logoMandante": "https://s.sde.globo.com/media/organizations/2021/09/04/ESCUDO-VASCO-RGB_30px.png",
    "logoVisitante": "https://s.sde.globo.com/media/organizations/2014/04/14/sao_paulo_30x30.png",
    "golsMandante": 0,
    "golsVisitante": 0,
    "placar": "0 x 0",
    "placarHT": null,
    "tempo": "",
    "tempoExtra": null,
    "status": "Agendado",
    "statusRaw": "NS",
    "liga": "Campeonato Brasileiro sub-20",
    "ligaId": null,
    "ligaOriginal": "Campeonato Brasileiro sub-20",
    "ligaLogo": null,
    "estadio": "Nivaldão",
    "cidade": null,
    "horario": "15:00",
    "timestamp": 1772388000000,
    "fonte": "globo",
    "transmissao": []
  },
  {
    "id": 346690,
    "mandante": "Paulista",
    "visitante": "Francana",
    "logoMandante": "https://s.sde.globo.com/media/organizations/2024/08/30/paulista-30-71829.png",
    "logoVisitante": "https://s.sde.globo.com/media/organizations/2011/07/12/_esc30-francana.png",
    "golsMandante": 0,
    "golsVisitante": 0,
    "placar": "0 x 0",
    "placarHT": null,
    "tempo": "",
    "tempoExtra": null,
    "status": "Agendado",
    "statusRaw": "NS",
    "liga": "Campeonato Paulista Série A3",
    "ligaId": null,
    "ligaOriginal": "Campeonato Paulista Série A3",
    "ligaLogo": null,
    "estadio": "Jayme Cintra",
    "cidade": null,
    "horario": "15:00",
    "timestamp": 1772388000000,
    "fonte": "globo",
    "transmissao": []
  },
  {
    "id": 347103,
    "mandante": "Águia Negra",
    "visitante": "Naviraiense",
    "logoMandante": "https://s.sde.globo.com/media/organizations/2012/01/12/aguiaNegra_MatoGrossodoSul30.png",
    "logoVisitante": "https://s.sde.globo.com/media/organizations/2025/01/15/30.png",
    "golsMandante": 0,
    "golsVisitante": 0,
    "placar": "0 x 0",
    "placarHT": null,
    "tempo": "",
    "tempoExtra": null,
    "status": "Agendado",
    "statusRaw": "NS",
    "liga": "Campeonato Sul-Mato-Grossense",
    "ligaId": null,
    "ligaOriginal": "Campeonato Sul-Mato-Grossense",
    "ligaLogo": null,
    "estadio": "Ninho da Águia",
    "cidade": null,
    "horario": "15:00",
    "timestamp": 1772388000000,
    "fonte": "globo",
    "transmissao": []
  },
  {
    "id": 347104,
    "mandante": "Dourados",
    "visitante": "CRA",
    "logoMandante": "https://s.sde.globo.com/media/organizations/2021/02/23/escudo-pequeno-38536.png",
    "logoVisitante": "https://s.sde.globo.com/media/organizations/2025/11/19/30-_0000_CRA-LOGO-2025.png",
    "golsMandante": 0,
    "golsVisitante": 0,
    "placar": "0 x 0",
    "placarHT": null,
    "tempo": "",
    "tempoExtra": null,
    "status": "Agendado",
    "statusRaw": "NS",
    "liga": "Campeonato Sul-Mato-Grossense",
    "ligaId": null,
    "ligaOriginal": "Campeonato Sul-Mato-Grossense",
    "ligaLogo": null,
    "estadio": "Douradão",
    "cidade": null,
    "horario": "15:00",
    "timestamp": 1772388000000,
    "fonte": "globo",
    "transmissao": []
  },
  {
    "id": 347105,
    "mandante": "Pantanal",
    "visitante": "Ivinhema",
    "logoMandante": "https://s.sde.globo.com/media/organizations/2025/01/15/30_6ZWDWnq.png",
    "logoVisitante": "https://s.sde.globo.com/media/organizations/2023/12/12/ivinhema-30.png",
    "golsMandante": 0,
    "golsVisitante": 0,
    "placar": "0 x 0",
    "placarHT": null,
    "tempo": "",
    "tempoExtra": null,
    "status": "Agendado",
    "statusRaw": "NS",
    "liga": "Campeonato Sul-Mato-Grossense",
    "ligaId": null,
    "ligaOriginal": "Campeonato Sul-Mato-Grossense",
    "ligaLogo": null,
    "estadio": "Moreninhas",
    "cidade": null,
    "horario": "15:00",
    "timestamp": 1772388000000,
    "fonte": "globo",
    "transmissao": []
  },
  {
    "id": 347102,
    "mandante": "Costa Rica-MS",
    "visitante": "Corumbaense",
    "logoMandante": "https://s.sde.globo.com/media/organizations/2013/10/11/costaricaec-ms30.png",
    "logoVisitante": "https://s.sde.globo.com/media/teams/2013/09/16/Corumbaense-30.png",
    "golsMandante": 0,
    "golsVisitante": 0,
    "placar": "0 x 0",
    "placarHT": null,
    "tempo": "",
    "tempoExtra": null,
    "status": "Agendado",
    "statusRaw": "NS",
    "liga": "Campeonato Sul-Mato-Grossense",
    "ligaId": null,
    "ligaOriginal": "Campeonato Sul-Mato-Grossense",
    "ligaLogo": null,
    "estadio": "Laertão",
    "cidade": null,
    "horario": "15:00",
    "timestamp": 1772388000000,
    "fonte": "globo",
    "transmissao": []
  },
  {
    "id": 340784,
    "mandante": "Hamburgo",
    "visitante": "RB Leipzig",
    "logoMandante": "https://s.sde.globo.com/media/organizations/2012/04/27/Hamburgo30.png",
    "logoVisitante": "https://s.sde.globo.com/media/organizations/2023/08/18/rb30.png",
    "golsMandante": 0,
    "golsVisitante": 0,
    "placar": "0 x 0",
    "placarHT": null,
    "tempo": "",
    "tempoExtra": null,
    "status": "Agendado",
    "statusRaw": "NS",
    "liga": "Bundesliga",
    "ligaId": null,
    "ligaOriginal": "Bundesliga",
    "ligaLogo": null,
    "estadio": "Volkspark",
    "cidade": null,
    "horario": "15:30",
    "timestamp": 1772389800000,
    "fonte": "globo",
    "transmissao": [
      "Prime Vídeo"
    ]
  },
  {
    "id": 346986,
    "mandante": "Parintins",
    "visitante": "Amazonas",
    "logoMandante": "https://s.sde.globo.com/media/organizations/2024/01/24/Parintins_30.png",
    "logoVisitante": "https://s.sde.globo.com/media/organizations/2024/08/20/amazonas-novo-30.png",
    "golsMandante": 0,
    "golsVisitante": 0,
    "placar": "0 x 0",
    "placarHT": null,
    "tempo": "",
    "tempoExtra": null,
    "status": "Agendado",
    "statusRaw": "NS",
    "liga": "Campeonato Amazonense",
    "ligaId": null,
    "ligaOriginal": "Campeonato Amazonense",
    "ligaLogo": null,
    "estadio": "Chicão",
    "cidade": null,
    "horario": "15:30",
    "timestamp": 1772389800000,
    "fonte": "globo",
    "transmissao": []
  },
  {
    "id": 347632,
    "mandante": "Rio Branco-PR",
    "visitante": "Laranja Mecânica",
    "logoMandante": "https://s.sde.globo.com/media/organizations/2022/12/19/30.png",
    "logoVisitante": "https://s.sde.globo.com/media/organizations/2026/02/26/30-_0001_laranja-mecanica_1.png",
    "golsMandante": 0,
    "golsVisitante": 0,
    "placar": "0 x 0",
    "placarHT": null,
    "tempo": "",
    "tempoExtra": null,
    "status": "Agendado",
    "statusRaw": "NS",
    "liga": "Campeonato Paranaense Segunda Divisão",
    "ligaId": null,
    "ligaOriginal": "Campeonato Paranaense Segunda Divisão",
    "ligaLogo": null,
    "estadio": "Gigante do Itiberê",
    "cidade": null,
    "horario": "15:30",
    "timestamp": 1772389800000,
    "fonte": "globo",
    "transmissao": []
  },
  {
    "id": 347628,
    "mandante": "Paranavaí",
    "visitante": "Araucária",
    "logoMandante": "https://s.sde.globo.com/media/organizations/2024/05/20/Atletico_Clube_Paranavai_30x30.png",
    "logoVisitante": "https://s.sde.globo.com/media/organizations/2023/03/20/araucaria-30px-59360.png",
    "golsMandante": 0,
    "golsVisitante": 0,
    "placar": "0 x 0",
    "placarHT": null,
    "tempo": "",
    "tempoExtra": null,
    "status": "Agendado",
    "statusRaw": "NS",
    "liga": "Campeonato Paranaense Segunda Divisão",
    "ligaId": null,
    "ligaOriginal": "Campeonato Paranaense Segunda Divisão",
    "ligaLogo": null,
    "estadio": "Felipão (PR)",
    "cidade": null,
    "horario": "15:30",
    "timestamp": 1772389800000,
    "fonte": "globo",
    "transmissao": []
  },
  {
    "id": 347631,
    "mandante": "Nacional-PR",
    "visitante": "Toledo",
    "logoMandante": "https://s.sde.globo.com/media/organizations/2026/02/26/30-_0000_nacional-pr.png",
    "logoVisitante": "https://s.sde.globo.com/media/organizations/2019/02/28/escudo_toledo_35.png",
    "golsMandante": 0,
    "golsVisitante": 0,
    "placar": "0 x 0",
    "placarHT": null,
    "tempo": "",
    "tempoExtra": null,
    "status": "Agendado",
    "statusRaw": "NS",
    "liga": "Campeonato Paranaense Segunda Divisão",
    "ligaId": null,
    "ligaOriginal": "Campeonato Paranaense Segunda Divisão",
    "ligaLogo": null,
    "estadio": "Estádio dos Amadores",
    "cidade": null,
    "horario": "15:30",
    "timestamp": 1772389800000,
    "fonte": "globo",
    "transmissao": []
  },
  {
    "id": 348743,
    "mandante": "Ji-Paraná",
    "visitante": "União Cacoalense",
    "logoMandante": "https://s.sde.globo.com/media/organizations/2026/02/11/30_Ji-Paraná-RO.png",
    "logoVisitante": "https://s.sde.globo.com/media/organizations/2026/01/07/uniao-cacolense-30-79613.png",
    "golsMandante": 0,
    "golsVisitante": 0,
    "placar": "0 x 0",
    "placarHT": null,
    "tempo": "",
    "tempoExtra": null,
    "status": "Agendado",
    "statusRaw": "NS",
    "liga": "Campeonato Rondoniense",
    "ligaId": null,
    "ligaOriginal": "Campeonato Rondoniense",
    "ligaLogo": null,
    "estadio": "Cassolão",
    "cidade": null,
    "horario": "15:30",
    "timestamp": 1772389800000,
    "fonte": "globo",
    "transmissao": []
  },
  {
    "id": 346988,
    "mandante": "Princesa do Solimões",
    "visitante": "Nacional-AM",
    "logoMandante": "https://s.sde.globo.com/media/organizations/2012/04/27/princesa-do-solimoes30.png",
    "logoVisitante": "https://s.sde.globo.com/media/organizations/2023/04/28/NACIONAL-AM-30.png",
    "golsMandante": 0,
    "golsVisitante": 0,
    "placar": "0 x 0",
    "placarHT": null,
    "tempo": "",
    "tempoExtra": null,
    "status": "Agendado",
    "statusRaw": "NS",
    "liga": "Campeonato Amazonense",
    "ligaId": null,
    "ligaOriginal": "Campeonato Amazonense",
    "ligaLogo": null,
    "estadio": "Gilbertão (AM)",
    "cidade": null,
    "horario": "16:00",
    "timestamp": 1772391600000,
    "fonte": "globo",
    "transmissao": []
  },
  {
    "id": 349553,
    "mandante": "Vitória-ES",
    "visitante": "Forte",
    "logoMandante": "https://s.sde.globo.com/media/organizations/2025/08/27/Novo-Escudo-Vitoria-ES-2025-30x30.png",
    "logoVisitante": "https://s.sde.globo.com/media/teams/2025/10/06/Forte-FC-30.png",
    "golsMandante": 0,
    "golsVisitante": 0,
    "placar": "0 x 0",
    "placarHT": null,
    "tempo": "",
    "tempoExtra": null,
    "status": "Agendado",
    "statusRaw": "NS",
    "liga": "Campeonato Capixaba",
    "ligaId": null,
    "ligaOriginal": "Campeonato Capixaba",
    "ligaLogo": null,
    "estadio": "Salvador Costa",
    "cidade": null,
    "horario": "16:00",
    "timestamp": 1772391600000,
    "fonte": "globo",
    "transmissao": []
  },
  {
    "id": 349567,
    "mandante": "IAPE",
    "visitante": "Maranhão",
    "logoMandante": "https://s.sde.globo.com/media/organizations/2022/04/03/30-iape.png",
    "logoVisitante": "https://s.sde.globo.com/media/teams/2012/03/01/maranhao_30.png",
    "golsMandante": 0,
    "golsVisitante": 0,
    "placar": "0 x 0",
    "placarHT": null,
    "tempo": "",
    "tempoExtra": null,
    "status": "Agendado",
    "statusRaw": "NS",
    "liga": "Campeonato Maranhense",
    "ligaId": null,
    "ligaOriginal": "Campeonato Maranhense",
    "ligaLogo": null,
    "estadio": "Nhozinho Santos",
    "cidade": null,
    "horario": "16:00",
    "timestamp": 1772391600000,
    "fonte": "globo",
    "transmissao": []
  },
  {
    "id": 347836,
    "mandante": "Murici",
    "visitante": "Miguelense",
    "logoMandante": "https://s.sde.globo.com/media/teams/2025/12/22/30_Murici.png",
    "logoVisitante": "https://s.sde.globo.com/media/teams/2016/12/05/Miguelense_30.png",
    "golsMandante": 0,
    "golsVisitante": 0,
    "placar": "0 x 0",
    "placarHT": null,
    "tempo": "",
    "tempoExtra": null,
    "status": "Agendado",
    "statusRaw": "NS",
    "liga": "Copa Alagoas",
    "ligaId": null,
    "ligaOriginal": "Copa Alagoas",
    "ligaLogo": null,
    "estadio": "José Gomes da Costa",
    "cidade": null,
    "horario": "16:00",
    "timestamp": 1772391600000,
    "fonte": "globo",
    "transmissao": []
  },
  {
    "id": 340092,
    "mandante": "Roma",
    "visitante": "Juventus",
    "logoMandante": "https://s.sde.globo.com/media/teams/2017/06/05/ROMA-30.png",
    "logoVisitante": "https://s.sde.globo.com/media/organizations/2025/06/27/30_Juventus.png",
    "golsMandante": 0,
    "golsVisitante": 0,
    "placar": "0 x 0",
    "placarHT": null,
    "tempo": "",
    "tempoExtra": null,
    "status": "Agendado",
    "statusRaw": "NS",
    "liga": "Campeonato Italiano",
    "ligaId": null,
    "ligaOriginal": "Campeonato Italiano",
    "ligaLogo": null,
    "estadio": "Olímpico de Roma",
    "cidade": null,
    "horario": "16:45",
    "timestamp": 1772394300000,
    "fonte": "globo",
    "transmissao": [
      "Disney+"
    ]
  },
  {
    "id": 340428,
    "mandante": "Olympique de Marselha",
    "visitante": "Lyon",
    "logoMandante": "https://s.sde.globo.com/media/teams/2016/02/12/OlimpiqueMarsella-30.png",
    "logoVisitante": "https://s.sde.globo.com/media/organizations/2018/11/07/lyon-30x30.png",
    "golsMandante": 0,
    "golsVisitante": 0,
    "placar": "0 x 0",
    "placarHT": null,
    "tempo": "",
    "tempoExtra": null,
    "status": "Agendado",
    "statusRaw": "NS",
    "liga": "Campeonato Francês",
    "ligaId": null,
    "ligaOriginal": "Campeonato Francês",
    "ligaLogo": null,
    "estadio": "Velódrome",
    "cidade": null,
    "horario": "16:45",
    "timestamp": 1772394300000,
    "fonte": "globo",
    "transmissao": [
      "Prime Vídeo"
    ]
  },
  {
    "id": 349421,
    "mandante": "Maricá",
    "visitante": "Nova Iguaçu",
    "logoMandante": "https://s.sde.globo.com/media/organizations/2024/12/26/marica-30.png",
    "logoVisitante": "https://s.sde.globo.com/media/organizations/2017/02/02/NovaIguacu-30.png",
    "golsMandante": 0,
    "golsVisitante": 0,
    "placar": "0 x 0",
    "placarHT": null,
    "tempo": "",
    "tempoExtra": null,
    "status": "Agendado",
    "statusRaw": "NS",
    "liga": "Campeonato Carioca",
    "ligaId": null,
    "ligaOriginal": "Campeonato Carioca",
    "ligaLogo": null,
    "estadio": "João Saldanha",
    "cidade": null,
    "horario": "17:00",
    "timestamp": 1772395200000,
    "fonte": "globo",
    "transmissao": []
  },
  {
    "id": 349637,
    "mandante": "North",
    "visitante": "Uberlândia",
    "logoMandante": "https://s.sde.globo.com/media/teams/2022/08/02/North_Esporte_Clube_2.png",
    "logoVisitante": "https://s.sde.globo.com/media/organizations/2011/01/21/uberlandia30x30.png",
    "golsMandante": 0,
    "golsVisitante": 0,
    "placar": "0 x 0",
    "placarHT": null,
    "tempo": "",
    "tempoExtra": null,
    "status": "Agendado",
    "statusRaw": "NS",
    "liga": "Campeonato Mineiro",
    "ligaId": null,
    "ligaOriginal": "Campeonato Mineiro",
    "ligaLogo": null,
    "estadio": "Arena Credinor",
    "cidade": null,
    "horario": "17:00",
    "timestamp": 1772395200000,
    "fonte": "globo",
    "transmissao": []
  },
  {
    "id": 339242,
    "mandante": "Girona",
    "visitante": "Celta",
    "logoMandante": "https://s.sde.globo.com/media/organizations/2023/12/20/30-_0006_Girona_FC.png",
    "logoVisitante": "https://s.sde.globo.com/media/organizations/2024/10/18/30_Celta-de-Vigo.png",
    "golsMandante": 0,
    "golsVisitante": 0,
    "placar": "0 x 0",
    "placarHT": null,
    "tempo": "",
    "tempoExtra": null,
    "status": "Agendado",
    "statusRaw": "NS",
    "liga": "La Liga",
    "ligaId": null,
    "ligaOriginal": "La Liga",
    "ligaLogo": null,
    "estadio": "Montilivi",
    "cidade": null,
    "horario": "17:00",
    "timestamp": 1772395200000,
    "fonte": "globo",
    "transmissao": [
      "Disney+",
      "Cartola"
    ]
  },
  {
    "id": 350118,
    "mandante": "Vitória",
    "visitante": "Jacuipense",
    "logoMandante": "https://s.sde.globo.com/media/organizations/2025/12/18/Vitoria-2025-30.png",
    "logoVisitante": "https://s.sde.globo.com/media/organizations/2019/01/08/Jacuipense30.png",
    "golsMandante": 0,
    "golsVisitante": 0,
    "placar": "0 x 0",
    "placarHT": null,
    "tempo": "",
    "tempoExtra": null,
    "status": "Agendado",
    "statusRaw": "NS",
    "liga": "Campeonato Baiano",
    "ligaId": null,
    "ligaOriginal": "Campeonato Baiano",
    "ligaLogo": null,
    "estadio": "Barradão",
    "cidade": null,
    "horario": "17:00",
    "timestamp": 1772395200000,
    "fonte": "globo",
    "transmissao": []
  },
  {
    "id": 349802,
    "mandante": "Vila Nova",
    "visitante": "Atlético-GO",
    "logoMandante": "https://s.sde.globo.com/media/organizations/2021/04/07/vilanova-30.png",
    "logoVisitante": "https://s.sde.globo.com/media/organizations/2020/07/02/atletico-go-2020-30.png",
    "golsMandante": 0,
    "golsVisitante": 0,
    "placar": "0 x 0",
    "placarHT": null,
    "tempo": "",
    "tempoExtra": null,
    "status": "Agendado",
    "statusRaw": "NS",
    "liga": "Campeonato Goiano",
    "ligaId": null,
    "ligaOriginal": "Campeonato Goiano",
    "ligaLogo": null,
    "estadio": "OBA",
    "cidade": null,
    "horario": "17:00",
    "timestamp": 1772395200000,
    "fonte": "globo",
    "transmissao": []
  },
  {
    "id": 350189,
    "mandante": "Mixto-MT",
    "visitante": "Luverdense",
    "logoMandante": "https://s.sde.globo.com/media/organizations/2018/12/13/mixto-mt-30.png",
    "logoVisitante": "https://s.sde.globo.com/media/organizations/2025/07/31/Luverdense_30x30.png",
    "golsMandante": 0,
    "golsVisitante": 0,
    "placar": "0 x 0",
    "placarHT": null,
    "tempo": "",
    "tempoExtra": null,
    "status": "Agendado",
    "statusRaw": "NS",
    "liga": "Campeonato Mato-Grossense",
    "ligaId": null,
    "ligaOriginal": "Campeonato Mato-Grossense",
    "ligaLogo": null,
    "estadio": "Dutrinha",
    "cidade": null,
    "horario": "17:00",
    "timestamp": 1772395200000,
    "fonte": "globo",
    "transmissao": [
      "Globo"
    ]
  },
  {
    "id": 350106,
    "mandante": "Remo",
    "visitante": "Paysandu",
    "logoMandante": "https://s.sde.globo.com/media/organizations/2013/10/11/REmo-30.png",
    "logoVisitante": "https://s.sde.globo.com/media/organizations/2019/05/29/Untitled-1-30.png",
    "golsMandante": 0,
    "golsVisitante": 0,
    "placar": "0 x 0",
    "placarHT": null,
    "tempo": "",
    "tempoExtra": null,
    "status": "Agendado",
    "statusRaw": "NS",
    "liga": "Campeonato Paraense",
    "ligaId": null,
    "ligaOriginal": "Campeonato Paraense",
    "ligaLogo": null,
    "estadio": "Mangueirão",
    "cidade": null,
    "horario": "17:00",
    "timestamp": 1772395200000,
    "fonte": "globo",
    "transmissao": []
  },
  {
    "id": 348742,
    "mandante": "Porto Velho",
    "visitante": "Guaporé",
    "logoMandante": "https://s.sde.globo.com/media/organizations/2024/07/25/porto-velho-30x30.png",
    "logoVisitante": "https://s.sde.globo.com/media/organizations/2026/02/11/30_Guaporé.png",
    "golsMandante": 0,
    "golsVisitante": 0,
    "placar": "0 x 0",
    "placarHT": null,
    "tempo": "",
    "tempoExtra": null,
    "status": "Agendado",
    "statusRaw": "NS",
    "liga": "Campeonato Rondoniense",
    "ligaId": null,
    "ligaOriginal": "Campeonato Rondoniense",
    "ligaLogo": null,
    "estadio": "Aluizão",
    "cidade": null,
    "horario": "17:00",
    "timestamp": 1772395200000,
    "fonte": "globo",
    "transmissao": []
  },
  {
    "id": 348073,
    "mandante": "GAS",
    "visitante": "São Raimundo-RR",
    "logoMandante": "https://s.sde.globo.com/media/organizations/2017/04/20/gas_30.png",
    "logoVisitante": "https://s.sde.globo.com/media/organizations/2023/05/03/30-_0000_São_Raimundo_Esporte_Clube_RR.png",
    "golsMandante": 0,
    "golsVisitante": 0,
    "placar": "0 x 0",
    "placarHT": null,
    "tempo": "",
    "tempoExtra": null,
    "status": "Agendado",
    "statusRaw": "NS",
    "liga": "Campeonato Roraimense",
    "ligaId": null,
    "ligaOriginal": "Campeonato Roraimense",
    "ligaLogo": null,
    "estadio": "Canarinho",
    "cidade": null,
    "horario": "17:00",
    "timestamp": 1772395200000,
    "fonte": "globo",
    "transmissao": []
  },
  {
    "id": 350092,
    "mandante": "Sergipe",
    "visitante": "América de Propriá",
    "logoMandante": "https://s.sde.globo.com/media/organizations/2024/04/13/sergipe-escudo-69367.png",
    "logoVisitante": "https://s.sde.globo.com/media/organizations/2026/02/08/AmericaSE-30x30.png",
    "golsMandante": 0,
    "golsVisitante": 0,
    "placar": "0 x 0",
    "placarHT": null,
    "tempo": "",
    "tempoExtra": null,
    "status": "Agendado",
    "statusRaw": "NS",
    "liga": "Campeonato Sergipano",
    "ligaId": null,
    "ligaOriginal": "Campeonato Sergipano",
    "ligaLogo": null,
    "estadio": "Batistão (SE)",
    "cidade": null,
    "horario": "17:00",
    "timestamp": 1772395200000,
    "fonte": "globo",
    "transmissao": []
  },
  {
    "id": 349805,
    "mandante": "Fluminense",
    "visitante": "Vasco",
    "logoMandante": "https://s.sde.globo.com/media/organizations/2015/01/12/Fluminense-escudo.png",
    "logoVisitante": "https://s.sde.globo.com/media/organizations/2021/09/04/ESCUDO-VASCO-RGB_30px.png",
    "golsMandante": 0,
    "golsVisitante": 0,
    "placar": "0 x 0",
    "placarHT": null,
    "tempo": "",
    "tempoExtra": null,
    "status": "Agendado",
    "statusRaw": "NS",
    "liga": "Campeonato Carioca",
    "ligaId": null,
    "ligaOriginal": "Campeonato Carioca",
    "ligaLogo": null,
    "estadio": "Maracanã",
    "cidade": null,
    "horario": "18:00",
    "timestamp": 1772398800000,
    "fonte": "globo",
    "transmissao": [
      "sportv",
      "Premiere",
      "Globo",
      "globoplay",
      "Ge TV"
    ]
  },
  {
    "id": 349592,
    "mandante": "América-MG",
    "visitante": "Atlético-MG",
    "logoMandante": "https://s.sde.globo.com/media/organizations/2024/05/07/AMRICA-mg-30.png",
    "logoVisitante": "https://s.sde.globo.com/media/organizations/2017/11/23/Atletico-Mineiro-escudo30px.png",
    "golsMandante": 0,
    "golsVisitante": 0,
    "placar": "0 x 0",
    "placarHT": null,
    "tempo": "",
    "tempoExtra": null,
    "status": "Agendado",
    "statusRaw": "NS",
    "liga": "Campeonato Mineiro",
    "ligaId": null,
    "ligaOriginal": "Campeonato Mineiro",
    "ligaLogo": null,
    "estadio": "Independência",
    "cidade": null,
    "horario": "18:00",
    "timestamp": 1772398800000,
    "fonte": "globo",
    "transmissao": [
      "sportv",
      "Premiere",
      "Globo",
      "globoplay",
      "Ge TV"
    ]
  },
  {
    "id": 350115,
    "mandante": "Grêmio",
    "visitante": "Internacional",
    "logoMandante": "https://s.sde.globo.com/media/organizations/2014/04/14/gremio_30x30.png",
    "logoVisitante": "https://s.sde.globo.com/media/organizations/2016/05/03/inter30.png",
    "golsMandante": 0,
    "golsVisitante": 0,
    "placar": "0 x 0",
    "placarHT": null,
    "tempo": "",
    "tempoExtra": null,
    "status": "Agendado",
    "statusRaw": "NS",
    "liga": "Campeonato Gaúcho",
    "ligaId": null,
    "ligaOriginal": "Campeonato Gaúcho",
    "ligaLogo": null,
    "estadio": "Arena do Grêmio",
    "cidade": null,
    "horario": "18:00",
    "timestamp": 1772398800000,
    "fonte": "globo",
    "transmissao": [
      "sportv",
      "Premiere",
      "Globo",
      "globoplay"
    ]
  },
  {
    "id": 350123,
    "mandante": "Barra-SC",
    "visitante": "Chapecoense",
    "logoMandante": "https://s.sde.globo.com/media/organizations/2021/12/12/barra-sc-30-48126.png",
    "logoVisitante": "https://s.sde.globo.com/media/organizations/2021/06/21/chapecoense30.png",
    "golsMandante": 0,
    "golsVisitante": 0,
    "placar": "0 x 0",
    "placarHT": null,
    "tempo": "",
    "tempoExtra": null,
    "status": "Agendado",
    "statusRaw": "NS",
    "liga": "Campeonato Catarinense",
    "ligaId": null,
    "ligaOriginal": "Campeonato Catarinense",
    "ligaLogo": null,
    "estadio": "Arena Barra FC",
    "cidade": null,
    "horario": "18:00",
    "timestamp": 1772398800000,
    "fonte": "globo",
    "transmissao": [
      "Globo"
    ]
  },
  {
    "id": 350103,
    "mandante": "Fortaleza",
    "visitante": "Ceará",
    "logoMandante": "https://s.sde.globo.com/media/organizations/2021/09/19/30_0000_Fortaleza-2021.png",
    "logoVisitante": "https://s.sde.globo.com/media/organizations/2019/10/10/ceara-30x30.png",
    "golsMandante": 0,
    "golsVisitante": 0,
    "placar": "0 x 0",
    "placarHT": null,
    "tempo": "",
    "tempoExtra": null,
    "status": "Agendado",
    "statusRaw": "NS",
    "liga": "Campeonato Cearense",
    "ligaId": null,
    "ligaOriginal": "Campeonato Cearense",
    "ligaLogo": null,
    "estadio": "Castelão (CE)",
    "cidade": null,
    "horario": "18:00",
    "timestamp": 1772398800000,
    "fonte": "globo",
    "transmissao": [
      "Globo",
      "globoplay"
    ]
  },
  {
    "id": 350111,
    "mandante": "Serra Branca",
    "visitante": "Botafogo-PB",
    "logoMandante": "https://s.sde.globo.com/media/organizations/2025/01/03/serra-branca-30x30.png",
    "logoVisitante": "https://s.sde.globo.com/media/organizations/2020/02/12/bot30.png",
    "golsMandante": 0,
    "golsVisitante": 0,
    "placar": "0 x 0",
    "placarHT": null,
    "tempo": "",
    "tempoExtra": null,
    "status": "Agendado",
    "statusRaw": "NS",
    "liga": "Campeonato Paraibano",
    "ligaId": null,
    "ligaOriginal": "Campeonato Paraibano",
    "ligaLogo": null,
    "estadio": "Amigão",
    "cidade": null,
    "horario": "18:00",
    "timestamp": 1772398800000,
    "fonte": "globo",
    "transmissao": [
      "Globo"
    ]
  },
  {
    "id": 350101,
    "mandante": "Sport",
    "visitante": "Náutico",
    "logoMandante": "https://s.sde.globo.com/media/organizations/2015/07/21/sport30.png",
    "logoVisitante": "https://s.sde.globo.com/media/organizations/2014/04/14/nautico_30x30.png",
    "golsMandante": 0,
    "golsVisitante": 0,
    "placar": "0 x 0",
    "placarHT": null,
    "tempo": "",
    "tempoExtra": null,
    "status": "Agendado",
    "statusRaw": "NS",
    "liga": "Campeonato Pernambucano",
    "ligaId": null,
    "ligaOriginal": "Campeonato Pernambucano",
    "ligaLogo": null,
    "estadio": "Ilha do Retiro",
    "cidade": null,
    "horario": "18:00",
    "timestamp": 1772398800000,
    "fonte": "globo",
    "transmissao": [
      "Globo",
      "globoplay"
    ]
  },
  {
    "id": 350120,
    "mandante": "Palmeiras",
    "visitante": "São Paulo",
    "logoMandante": "https://s.sde.globo.com/media/organizations/2014/04/14/palmeiras_30x30.png",
    "logoVisitante": "https://s.sde.globo.com/media/organizations/2014/04/14/sao_paulo_30x30.png",
    "golsMandante": 0,
    "golsVisitante": 0,
    "placar": "0 x 0",
    "placarHT": null,
    "tempo": "",
    "tempoExtra": null,
    "status": "Agendado",
    "statusRaw": "NS",
    "liga": "Campeonato Paulista",
    "ligaId": null,
    "ligaOriginal": "Campeonato Paulista",
    "ligaLogo": null,
    "estadio": "Arena Barueri",
    "cidade": null,
    "horario": "20:30",
    "timestamp": 1772407800000,
    "fonte": "globo",
    "transmissao": [
      "HBO Max"
    ]
  },
  {
    "id": 340088,
    "mandante": "Cremonese",
    "visitante": "Milan",
    "logoMandante": "https://s.sde.globo.com/media/organizations/2022/06/25/30-cremonese-534341.png",
    "logoVisitante": "https://s.sde.globo.com/media/teams/2013/09/16/milan_30x30.png",
    "golsMandante": 0,
    "golsVisitante": 2,
    "placar": "0 x 2",
    "placarHT": null,
    "tempo": "",
    "tempoExtra": null,
    "status": "Encerrado",
    "statusRaw": "FT",
    "liga": "Campeonato Italiano",
    "ligaId": null,
    "ligaOriginal": "Campeonato Italiano",
    "ligaLogo": null,
    "estadio": "Giovanni Zini",
    "cidade": null,
    "horario": "08:30",
    "timestamp": 1772364600000,
    "fonte": "globo",
    "transmissao": [
      "Disney+"
    ]
  }
]